area/__init__.py
area/shapes.py
area_codersao-0.1.dist-info/METADATA
area_codersao-0.1.dist-info/WHEEL
area_codersao-0.1.dist-info/top_level.txt
area_codersao-0.1.dist-info/RECORD
