Metadata-Version: 2.4
Name: area-codersao
Version: 0.1
Summary: A simple library to calculate area of shapes
Author: Jatin Ghoyal
Author-email: codersao@gmail.com
Dynamic: author
Dynamic: author-email
Dynamic: summary
